leaguemanager/__init__.py
leaguemanager/__main__.py
leaguemanager/__metadata__.py
leaguemanager/_types.py
leaguemanager/cli.py
leaguemanager/py.typed
leaguemanager/data/importer_templates/excel/Excel Template - Random User.xlsx
leaguemanager/data/importer_templates/excel/excel_import_template.xlsx
leaguemanager/data/importer_templates/excel/~$Excel Template - Random User.xlsx
leaguemanager/data/synthetic_data/example_data.json
leaguemanager/db/__init__.py
leaguemanager/db/config.py
leaguemanager/db/engine_factory.py
leaguemanager/db/sqlite3_datetime.py
leaguemanager/db/alembic_templates/__init__.py
leaguemanager/db/alembic_templates/asyncio/alembic.ini.mako
leaguemanager/db/alembic_templates/asyncio/env.py
leaguemanager/db/alembic_templates/asyncio/script.py.mako
leaguemanager/db/alembic_templates/sync/__init__.py
leaguemanager/db/alembic_templates/sync/alembic.ini.mako
leaguemanager/db/alembic_templates/sync/env.py
leaguemanager/db/alembic_templates/sync/script.py.mako
leaguemanager/db/cli/__init__.py
leaguemanager/db/cli/alembic_cli.py
leaguemanager/dependency/__init__.py
leaguemanager/dependency/cli_callbacks.py
leaguemanager/dependency/dependency_registry.py
leaguemanager/dependency/loader.py
leaguemanager/dependency/managers.py
leaguemanager/ext/litestar/__init__.py
leaguemanager/ext/litestar/attrs_dto.py
leaguemanager/ext/litestar/config.py
leaguemanager/ext/litestar/oauth.py
leaguemanager/ext/litestar/plugin.py
leaguemanager/ext/litestar/svcs_middleware.py
leaguemanager/ext/litestar/auth/__init__.py
leaguemanager/lib/__init__.py
leaguemanager/lib/email.py
leaguemanager/lib/exceptions.py
leaguemanager/lib/oauth.py
leaguemanager/lib/security.py
leaguemanager/lib/settings.py
leaguemanager/lib/toolbox.py
leaguemanager/lib/validation.py
leaguemanager/models/__init__.py
leaguemanager/models/_states.py
leaguemanager/models/_types.py
leaguemanager/models/base.py
leaguemanager/models/enums.py
leaguemanager/models/slug.py
leaguemanager/models/account/__init__.py
leaguemanager-0.15.2.dist-info/METADATA
leaguemanager-0.15.2.dist-info/WHEEL
leaguemanager-0.15.2.dist-info/entry_points.txt
leaguemanager-0.15.2.dist-info/licenses/LICENSE
leaguemanager-0.15.2.dist-info/RECORD
