Metadata-Version: 2.4
Name: leaguemanager
Version: 0.15.2
Summary: Build and manage sports leagues.
Project-URL: Homepage, https://leaguemanager.readthedocs.io/en/latest/
Project-URL: Documentation, https://leaguemanager.readthedocs.io/en/latest/
Project-URL: Source, https://codeberg.org/pythonbynight/leaguemanager
Project-URL: Issue, https://codeberg.org/pythonbynight/leaguemanager/issues
Project-URL: Changelog, https://codeberg.org/pythonbynight/leaguemanager/releases
Author-email: Mario Munoz <pythonbynight@gmail.com>
License-File: LICENSE
Keywords: advanced alchemy,alembic,league,sports,sqlalchemy
Classifier: Development Status :: 3 - Alpha
Classifier: Intended Audience :: Developers
Classifier: Natural Language :: English
Classifier: Operating System :: OS Independent
Classifier: Programming Language :: Python :: 3
Classifier: Programming Language :: Python :: 3.12
Classifier: Topic :: Software Development
Classifier: Typing :: Typed
Requires-Python: >=3.13
Requires-Dist: advanced-alchemy>=1.2.0
Requires-Dist: aiosqlite>=0.21.0
Requires-Dist: alembic>=1.15.2
Requires-Dist: attrs>=25.3.0
Requires-Dist: environ-config>=24.1.0
Requires-Dist: httpx-oauth>=0.16.1
Requires-Dist: openpyxl>=3.1.5
Requires-Dist: pandas>=2.3.1
Requires-Dist: passlib>=1.7.4
Requires-Dist: svcs>=25.1.0
Requires-Dist: typer>=0.15.2
Provides-Extra: litestar
Requires-Dist: litestar; extra == 'litestar'
Provides-Extra: postgres
Requires-Dist: asyncpg; extra == 'postgres'
Requires-Dist: psycopg2-binary; extra == 'postgres'
Requires-Dist: psycopg[binary,pool]; extra == 'postgres'
